dflow_hello/__init__.py
dflow_hello/hello.py
dflow_hello-0.1.7.dist-info/LICENSE
dflow_hello-0.1.7.dist-info/METADATA
dflow_hello-0.1.7.dist-info/WHEEL
dflow_hello-0.1.7.dist-info/top_level.txt
dflow_hello-0.1.7.dist-info/RECORD
