Metadata-Version: 2.1
Name: dflow-hello
Version: 0.1.7
Summary: dflow demo OP
Author: zjgemi
License: GNU LESSER GENERAL PUBLIC LICENSE
Project-URL: Source, https://github.com/zjgemi/dflow-hello
Keywords: dflow,OP
Classifier: Programming Language :: Python
Classifier: Intended Audience :: Science/Research
Classifier: License :: OSI Approved :: MIT License
Classifier: Natural Language :: English
Classifier: Development Status :: 3 - Alpha
Requires-Python: >=3.6
License-File: LICENSE
Requires-Dist: importlib-metadata
Requires-Dist: pydflow (>=1.0)
